marketwatch/__init__.py
marketwatch/exceptions.py
marketwatch/game.py
marketwatch/schemas.py
marketwatch/watchlist.py
marketwatch-0.2.4.2.dist-info/LICENSE
marketwatch-0.2.4.2.dist-info/METADATA
marketwatch-0.2.4.2.dist-info/WHEEL
marketwatch-0.2.4.2.dist-info/RECORD
