Metadata-Version: 2.1
Name: marketwatch
Version: 0.2.4.2
Summary: MarketWatch's API
Home-page: http://github.com/antoineboucher/marketwatch
License: Apache-2.0
Keywords: marketwatch,api,stock,finance,market,game
Author: Antoine Boucher
Author-email: antoine.boucher012@gmail.com
Requires-Python: >=3.8,<4.0
Classifier: Development Status :: 4 - Beta
Classifier: Intended Audience :: Developers
Classifier: License :: OSI Approved :: Apache Software License
Classifier: License :: OSI Approved :: MIT License
Classifier: Operating System :: OS Independent
Classifier: Programming Language :: Python :: 3
Classifier: Programming Language :: Python :: 3.8
Classifier: Programming Language :: Python :: 3.9
Classifier: Programming Language :: Python :: 3.10
Classifier: Programming Language :: Python :: 3.11
Classifier: Programming Language :: Python :: 3.12
Classifier: Topic :: Software Development :: Libraries :: Python Modules
Classifier: Typing :: Typed
Requires-Dist: beautifulsoup4 (>=4.12.0,<5.0.0)
Requires-Dist: httpx (>=0.27.0,<0.28.0)
Requires-Dist: rich (>=13.3.2,<14.0.0)
Project-URL: Documentation, https://antoinebou12.github.io/marketwatch/api/
Project-URL: Repository, http://github.com/antoineboucher/marketwatch
